receipt_trainer/__init__.py
receipt_trainer/config.py
receipt_trainer/constants.py
receipt_trainer/trainer.py
receipt_trainer/version.py
receipt_trainer/utils/__init__.py
receipt_trainer/utils/aws.py
receipt_trainer/utils/data.py
receipt_trainer-0.1.0.dist-info/METADATA
receipt_trainer-0.1.0.dist-info/WHEEL
receipt_trainer-0.1.0.dist-info/RECORD
