Metadata-Version: 2.4
Name: receipt_trainer
Version: 0.1.0
Summary: A package for training LayoutLM models on receipt data
Author-email: Tyler Norlund <tnorlund@icloud.com>
Classifier: License :: OSI Approved :: MIT License
Classifier: Operating System :: OS Independent
Classifier: Programming Language :: Python :: 3
Requires-Python: >=3.8
Requires-Dist: boto3>=1.26.0
Requires-Dist: datasets>=2.12.0
Requires-Dist: matplotlib>=3.7.0
Requires-Dist: numpy>=1.24.0
Requires-Dist: pulumi-aws>=6.0.0
Requires-Dist: pulumi>=3.0.0
Requires-Dist: scikit-learn>=1.3.0
Requires-Dist: seaborn>=0.12.0
Requires-Dist: torch>=2.0.0
Requires-Dist: transformers>=4.30.0
Requires-Dist: wandb>=0.15.0
Provides-Extra: dev
Requires-Dist: black>=22.0.0; extra == 'dev'
Requires-Dist: flake8>=6.0.0; extra == 'dev'
Requires-Dist: isort>=5.0.0; extra == 'dev'
Requires-Dist: mypy>=1.0.0; extra == 'dev'
Requires-Dist: pytest-cov>=4.0.0; extra == 'dev'
Requires-Dist: pytest>=7.0.0; extra == 'dev'
